Metadata-Version: 2.1
Name: matmalibka
Version: 0.0.1
Summary: Standardowa biblioteka
Home-page: 
Author: Mocusiek
Author-email: testomail123321@gmail.com
License: MIT
Keywords: matmalibka
Classifier: Development Status :: 5 - Production/Stable
Classifier: Intended Audience :: Education
Classifier: Operating System :: Microsoft :: Windows :: Windows 10
Classifier: License :: OSI Approved :: MIT License
Classifier: Programming Language :: Python :: 3
License-File: LICENSE.txt
